LICENSE.txt
README.md
setup.cfg
setup.py
openvpn_auth_duo/__init__.py
openvpn_auth_duo/_version.py
openvpn_auth_duo/authenticator.py
openvpn_auth_duo/duo_authenticator.py
openvpn_auth_duo/duo_cli.py
openvpn_auth_duo/schema.sql
openvpn_auth_duo/totp_authenticator.py
openvpn_auth_duo/totp_cli.py
openvpn_auth_duo.egg-info/PKG-INFO
openvpn_auth_duo.egg-info/SOURCES.txt
openvpn_auth_duo.egg-info/dependency_links.txt
openvpn_auth_duo.egg-info/entry_points.txt
openvpn_auth_duo.egg-info/requires.txt
openvpn_auth_duo.egg-info/top_level.txt
openvpn_auth_duo/openvpn/__init__.py
openvpn_auth_duo/util/__init__.py
openvpn_auth_duo/util/errors.py
openvpn_auth_duo/util/thread_pool.py