Metadata-Version: 2.1
Name: openvpn-auth-duo
Version: 1.3
Summary: openvpn-auth-duo connects to the openvpn management interface and handle the authentication against duo.
Home-page: https://github.com/crazy-penguins/openvpn-auth-duo
Author: crazy penguins
Author-email: pshingavi@gmail.com,
License: MIT
Download-URL: https://github.com/crazy-penguins/openvpn-auth-duo/archive/v1.3.tar.gz
Project-URL: Changelog, https://github.com/crazy-penguins/openvpn-auth-duo/blob/v1.3/CHANGELOG.md
Project-URL: Source, https://github.com/crazy-penguins/openvpn-auth-duo
Project-URL: Bug Reports, https://github.com/crazy-penguins/openvpn-auth-duo/issues
Keywords: OpenVPN,AzureAD,authentication,duo
Platform: UNKNOWN
Classifier: Programming Language :: Python :: 3
Classifier: License :: OSI Approved :: MIT License
Classifier: Operating System :: OS Independent
Classifier: Development Status :: 5 - Production/Stable
Classifier: Environment :: Console
Classifier: Topic :: System :: Systems Administration :: Authentication/Directory
License-File: LICENSE.txt
